mayfly/__init__.py
mayfly-0.0.0.dist-info/METADATA
mayfly-0.0.0.dist-info/WHEEL
mayfly-0.0.0.dist-info/top_level.txt
mayfly-0.0.0.dist-info/RECORD
