Metadata-Version: 2.1
Name: mayfly
Version: 0.0.0
Summary: Coming soon
Author-email: Dylan Wichman <dwichman125@gmail.com>
